LICENSE
README.md
setup.py
src/mathematic_package_reza.egg-info/PKG-INFO
src/mathematic_package_reza.egg-info/SOURCES.txt
src/mathematic_package_reza.egg-info/dependency_links.txt
src/mathematic_package_reza.egg-info/top_level.txt
src/mathematic_reza/__init__.py
src/mathematic_reza/aritmatika.py
src/mathematic_reza/bangun.py