Metadata-Version: 2.1
Name: mathematic-package-reza
Version: 1.3.0
Summary: matematika untuk python
Home-page: https://github.com/pypa/sampleproject
Author: Muhamad Reza Maulana
Author-email: maulana32.rm@gmail.com
License: UNKNOWN
Project-URL: Bug Tracker, https://github.com/pypa/sampleproject/issues
Platform: UNKNOWN
Classifier: Programming Language :: Python :: 3
Classifier: License :: OSI Approved :: MIT License
Classifier: Operating System :: OS Independent
Requires-Python: >=3.6
License-File: LICENSE
